massspecgym/__init__.py
massspecgym/definitions.py
massspecgym/feat_utils.py
massspecgym/utils.py
massspecgym/data/__init__.py
massspecgym/data/data_module.py
massspecgym/data/datasets.py
massspecgym/data/transforms.py
massspecgym/data/transforms_with_docstrings_cleaned.py
massspecgym/data/transforms_with_docstrings_fixed.py
massspecgym/models/__init__.py
massspecgym/models/base.py
massspecgym/models/layers.py
massspecgym/models/tokenizers.py
massspecgym/models/de_novo/__init__.py
massspecgym/models/de_novo/base.py
massspecgym/models/de_novo/dummy.py
massspecgym/models/de_novo/random.py
massspecgym/models/de_novo/smiles_tranformer.py
massspecgym/models/retrieval/__init__.py
massspecgym/models/retrieval/base.py
massspecgym/models/retrieval/deepsets.py
massspecgym/models/retrieval/fingerprint_ffn.py
massspecgym/models/retrieval/from_dict.py
massspecgym/models/retrieval/random.py
massspecgym/models/simulation/__init__.py
massspecgym/models/simulation/base.py
massspecgym/models/simulation/fp.py
massspecgym/models/simulation/gnn.py
massspecgym/models/simulation/prec_only.py
massspecgym/simulation_utils/__init__.py
massspecgym/simulation_utils/feat_utils.py
massspecgym/simulation_utils/formula_embedder.py
massspecgym/simulation_utils/misc_utils.py
massspecgym/simulation_utils/model_utils.py
massspecgym/simulation_utils/nn_utils.py
massspecgym/simulation_utils/run_utils.py
massspecgym/simulation_utils/spec_utils.py
massspecgym-1.3.1.dist-info/LICENCE
massspecgym-1.3.1.dist-info/METADATA
massspecgym-1.3.1.dist-info/WHEEL
massspecgym-1.3.1.dist-info/top_level.txt
massspecgym-1.3.1.dist-info/RECORD
