Metadata-Version: 2.1
Name: massspecgym
Version: 1.3.1
Summary: MassSpecGym: A benchmark for the discovery and identification of molecules
Author: MassSpecGym developers
Author-email: roman.bushuiev@uochb.cas.cz
License: MIT
Classifier: Programming Language :: Python :: 3.11
Classifier: License :: OSI Approved :: MIT License
Classifier: Operating System :: OS Independent
Requires-Python: >=3.11
License-File: LICENCE
Requires-Dist: torch ==2.3.0
Requires-Dist: pytorch-lightning ==2.2.5
Requires-Dist: torchmetrics ==1.4.0
Requires-Dist: torch-geometric ==2.5.3
Requires-Dist: tokenizers ==0.19.1
Requires-Dist: numpy ==1.24.4
Requires-Dist: rdkit ==2023.9.4
Requires-Dist: myopic-mces ==1.0.0
Requires-Dist: matchms ==0.26.2
Requires-Dist: wandb ==0.17.0
Requires-Dist: huggingface-hub ==0.23.2
Requires-Dist: seaborn ==0.13.2
Requires-Dist: chemparse ==0.3.1
Requires-Dist: chemformula ==1.3.1
Requires-Dist: networkx ==3.3
Requires-Dist: selfies ==2.1.2
Requires-Dist: pulp ==2.9.0
Provides-Extra: dev
Requires-Dist: black ==24.4.2 ; extra == 'dev'
Requires-Dist: pytest ==8.2.1 ; extra == 'dev'
Requires-Dist: pytest-cov ==5.0.0 ; extra == 'dev'
Provides-Extra: notebooks
Requires-Dist: jupyter ==1.0.0 ; extra == 'notebooks'
Requires-Dist: ipywidgets ==8.1.3 ; extra == 'notebooks'
Requires-Dist: h5py ==3.11.0 ; extra == 'notebooks'
Requires-Dist: scikit-learn ==1.5.0 ; extra == 'notebooks'
Requires-Dist: pandarallel ==1.6.5 ; extra == 'notebooks'
